annofab_3dpc/__init__.py
annofab_3dpc/__version__.py
annofab_3dpc/annotation.py
annofab_3dpc/py.typed
annofabapi_3dpc_extensions-0.3.0.dist-info/LICENSE
annofabapi_3dpc_extensions-0.3.0.dist-info/METADATA
annofabapi_3dpc_extensions-0.3.0.dist-info/WHEEL
annofabapi_3dpc_extensions-0.3.0.dist-info/RECORD
