Metadata-Version: 2.1
Name: annofabapi-3dpc-extensions
Version: 0.3.0
Summary: annofabapiの3DPC Editor用の拡張機能です。
Home-page: https://github.com/kurusugawa-computer/annofabapi-3dpc-extensions
Author: Kurusugawa Computer Inc.
Requires-Python: >=3.9,<4.0
Classifier: Development Status :: 4 - Beta
Classifier: Intended Audience :: Developers
Classifier: Operating System :: OS Independent
Classifier: Programming Language :: Python :: 3
Classifier: Programming Language :: Python :: 3.9
Classifier: Programming Language :: Python :: 3.10
Classifier: Programming Language :: Python :: 3.11
Classifier: Programming Language :: Python :: 3.12
Classifier: Programming Language :: Python :: 3.13
Classifier: Topic :: Utilities
Requires-Dist: dataclasses-json
Requires-Dist: numpy
Project-URL: Repository, https://github.com/kurusugawa-computer/annofabapi-3dpc-extensions
